kataloger/__init__.py
kataloger/__main__.py
kataloger/catalog_updater.py
kataloger/default.configuration.toml
kataloger/cli/__init__.py
kataloger/cli/argument_parser.py
kataloger/cli/cli.py
kataloger/cli/configuration_provider.py
kataloger/cli/update_print_helper.py
kataloger/data/__init__.py
kataloger/data/artifact_metadata.py
kataloger/data/artifact_update.py
kataloger/data/catalog.py
kataloger/data/configuration_data.py
kataloger/data/kataloger_arguments.py
kataloger/data/kataloger_configuration.py
kataloger/data/metadata_repository_info.py
kataloger/data/repository.py
kataloger/data/artifact/__init__.py
kataloger/data/artifact/artifact.py
kataloger/data/artifact/library.py
kataloger/data/artifact/plugin.py
kataloger/exceptions/__init__.py
kataloger/exceptions/kataloger_configuration_exception.py
kataloger/exceptions/kataloger_exception.py
kataloger/exceptions/kataloger_parse_exception.py
kataloger/helpers/__init__.py
kataloger/helpers/backport_helpers.py
kataloger/helpers/log_helpers.py
kataloger/helpers/path_helpers.py
kataloger/helpers/structural_matching_helpers.py
kataloger/helpers/toml_parse_helpers.py
kataloger/helpers/update_helpers.py
kataloger/helpers/xml_parse_helpers.py
kataloger/update_resolver/__init__.py
kataloger/update_resolver/base/__init__.py
kataloger/update_resolver/base/update_resolution.py
kataloger/update_resolver/base/update_resolver.py
kataloger/update_resolver/universal/__init__.py
kataloger/update_resolver/universal/universal_update_resolver.py
kataloger/update_resolver/universal/universal_version.py
kataloger/update_resolver/universal/universal_version_factory.py
kataloger/update_resolver/universal/version.py
kataloger/update_resolver/universal/version_factory.py
kataloger-0.4.0.dist-info/licenses/LICENSE
kataloger-0.4.0.dist-info/METADATA
kataloger-0.4.0.dist-info/WHEEL
kataloger-0.4.0.dist-info/entry_points.txt
kataloger-0.4.0.dist-info/top_level.txt
kataloger-0.4.0.dist-info/RECORD
