Metadata-Version: 2.4
Name: kataloger
Version: 0.4.0
Summary: CLI tool for projects that uses gradle version catalog to check dependency updates.
Author-email: Dzmitry Pryskoka <mr.priskoka@yandex.com>
License: Apache 2.0
Project-URL: GitHub, https://github.com/dzmpr/kataloger
Project-URL: Changelog, https://github.com/dzmpr/kataloger/releases
Classifier: Development Status :: 4 - Beta
Classifier: Environment :: Console
Classifier: Intended Audience :: Developers
Classifier: Operating System :: OS Independent
Classifier: Programming Language :: Python :: 3 :: Only
Classifier: License :: OSI Approved :: Apache Software License
Classifier: Topic :: Software Development :: Version Control
Classifier: Topic :: Utilities
Requires-Python: >=3.9
License-File: LICENSE
Requires-Dist: aiohttp==3.12.12
Requires-Dist: xmltodict==0.14.2
Requires-Dist: yarl==1.20.1
Requires-Dist: tomli==2.2.1; python_version < "3.11"
Dynamic: license-file
